Metadata-Version: 2.1
Name: texta-torch-tagger
Version: 2.0.2
Summary: texta-tagger
Home-page: https://git.texta.ee/texta/texta-torch-tagger-python
Author: TEXTA
Author-email: info@texta.ee
License: GPLv3
Platform: UNKNOWN
